CHANGES.txt
MANIFEST.in
README.txt
setup.py
src/gocept/__init__.py
src/gocept.arecibologger.egg-info/PKG-INFO
src/gocept.arecibologger.egg-info/SOURCES.txt
src/gocept.arecibologger.egg-info/dependency_links.txt
src/gocept.arecibologger.egg-info/not-zip-safe
src/gocept.arecibologger.egg-info/top_level.txt
src/gocept/arecibologger/__init__.py
src/gocept/arecibologger/configure.zcml
src/gocept/arecibologger/logger.py