Metadata-Version: 1.0
Name: gocept.arecibologger
Version: 0.1.2
Summary: Arecibo patch for Zope 2's site error log.
Home-page: UNKNOWN
Author: Christian Theune
Author-email: ct@gocept.com
License: ZPL
Keywords: logging
Platform: UNKNOWN
Classifier: Framework :: Plone
Classifier: Framework :: Zope2
Classifier: Intended Audience :: Developers
Classifier: Intended Audience :: System Administrators
Classifier: Topic :: System :: Logging
